aiger_ptltl/__init__.py
aiger_ptltl/ptltl.py
aiger_ptltl/test_ptltl.py
py_aiger_ptltl-3.1.2.dist-info/LICENSE
py_aiger_ptltl-3.1.2.dist-info/WHEEL
py_aiger_ptltl-3.1.2.dist-info/METADATA
py_aiger_ptltl-3.1.2.dist-info/RECORD
