Metadata-Version: 2.1
Name: py-aiger-ptltl
Version: 3.1.2
Summary: Library for generating (p)ast (t)ense (l)inear (t)emporal (l)ogic monitors as aiger circuits.
Home-page: https://github.com/mvcisback/py-aiger-past-ltl
License: MIT
Author: Marcell Vazquez-Chanlatte
Author-email: mvc@linux.com
Requires-Python: >=3.7,<4.0
Classifier: License :: OSI Approved :: MIT License
Classifier: Programming Language :: Python :: 3
Classifier: Programming Language :: Python :: 3.10
Classifier: Programming Language :: Python :: 3.7
Classifier: Programming Language :: Python :: 3.8
Classifier: Programming Language :: Python :: 3.9
Provides-Extra: with_bv
Requires-Dist: py-aiger (>=6.0.0,<7.0.0)
Requires-Dist: py-aiger-bv (>=4.5.2,<5.0.0); extra == "with_bv"
Project-URL: Repository, https://github.com/mvcisback/py-aiger-past-ltl
